lensify/__init__.py
lensify/cli.py
lensify/search.py
lensify-0.2.0.dist-info/licenses/LICENSE
lensify-0.2.0.dist-info/METADATA
lensify-0.2.0.dist-info/WHEEL
lensify-0.2.0.dist-info/entry_points.txt
lensify-0.2.0.dist-info/top_level.txt
lensify-0.2.0.dist-info/RECORD
