Metadata-Version: 2.4
Name: lensify
Version: 0.2.0
Summary: Lensify upgraded local semantic search
Home-page: https://github.com/wakeups1dd/lensify
Author: Siddhant Gangawane
Author-email: siddhantgangawane335@gmail.com
License: MIT
Classifier: Programming Language :: Python :: 3
Classifier: License :: OSI Approved :: MIT License
Classifier: Operating System :: OS Independent
Requires-Python: >=3.8
License-File: LICENSE
Requires-Dist: sentence-transformers; extra == "embeddings"
Requires-Dist: numpy
Requires-Dist: faiss-cpu
Requires-Dist: PyPDF2
Requires-Dist: scikit-learn
Requires-Dist: nltk
Requires-Dist: tqdm
Dynamic: license-file
Dynamic: summary
